README.md
setup.py
stallions/__init__.py
stallions/article.py
stallions/config.py
stallions/crawler.py
stallions/extractors.py
stallions/network.py
stallions/outputformat.py
stallions/parsers.py
stallions/version.py
stallions.egg-info/PKG-INFO
stallions.egg-info/SOURCES.txt
stallions.egg-info/dependency_links.txt
stallions.egg-info/requires.txt
stallions.egg-info/top_level.txt