Metadata-Version: 1.1
Name: stallions
Version: 0.0.18
Summary: Extract the content of the web page.
Home-page: https://git.rtbasia.com/galen/python_stallion
Author: galen
Author-email: galen.wang@rtbasia.com
License: UNKNOWN
Keywords: Web spider
Platform: UNKNOWN
Classifier: Programming Language :: Python :: 3.4
Classifier: Programming Language :: Python :: 3.5
Classifier: Programming Language :: Python :: 3.6
Classifier: Programming Language :: Python :: 3.7
